Workbook

Sheet Inputs
A1: CAC Solver Model Inputs
A3: Model Controls | D3: Channel Cost Assumptions
A4: Total Budget | B4: =SUM('Channel Summary'!F2:F4) -> 335253 | D4: Contact Channel | E4: Cost per Contact
A5: Target Customers | B5: =SUM('Channel Summary'!C2:C4) -> 5289 | D5: cellular | E5: 3
A6: Objective | B6: Max customers or Min overall CAC | D6: telephone | E6: 4.5
D7: unknown | E7: 1.5

Sheet Channel Summary
A1: Contact | B1: total records | C1: customers acquired | D1: total contacts | E1: avg contacts | F1: total estimated cost | G1: avg duration | H1: conversion rate | I1: estimated cac | J1: customers per 1000
A2: cellular | B2: 29285 | C2: 4369 | D2: 78780 | E2: 2.6901144 | F2: 236340 | G2: 263.01397 | H2: 0.149189 | I2: 54.094758 | J2: 18.486079
A3: unknown | B3: 13020 | C3: 530 | D3: 36293 | E3: 2.7874808 | F3: 54439.5 | G3: 252.34048 | H3: 0.04070661 | I3: 102.71604 | J3: 9.735578
A4: telephone | B4: 2906 | C4: 390 | D4: 9883 | E4: 3.4008947 | F4: 44473.5 | G4: 235.36614 | H4: 0.13420509 | I4: 114.03462 | J4: 8.7692671
A5: Total | B5: =SUM(B2:B4) -> 45211 | C5: =SUM(C2:C4) -> 5289 | D5: =SUM(D2:D4) -> 124956 | E5: =SUM(E2:E4) -> 8.8784899 | F5: =SUM(F2:F4) -> 335253 | G5: =SUM(G2:G4) -> 750.72058 | H5: =SUM(H2:H4) -> 0.3241007 | I5: =SUM(I2:I4) -> 270.84541 | J5: =SUM(J2:J4) -> 36.990925

Sheet Solver Table
A1: contact | B1: estimated cac | C1: conversion rate | D1: customers per 1000 | E1: max budget | F1: min budget | G1: budget allocation | H1: expected customers | I1: expected cost check
A2: cellular | B2: 54.094759 | C2: 0.149189 | D2: 18.486079 | E2: 220000 | F2: 150000 | G2: 220000 | H2: 4066.9375 | I2: =IF(AND(G2>=F2,G2<=E2),"OK","OUT OF RANGE") -> OK
A3: unknown | B3: 102.71604 | C3: 0.040706605 | D3: 9.735578 | E3: 35253 | F3: 15000 | G3: 35253 | H3: 343.20833 | I3: =IF(AND(G3>=F3,G3<=E3),"OK","OUT OF RANGE") -> OK
A4: telephone | B4: 114.03462 | C4: 0.13420509 | D4: 8.7692671 | E4: 80000 | F4: 40000 | G4: 80000 | H4: 701.54137 | I4: =IF(AND(G4>=F4,G4<=E4),"OK","OUT OF RANGE") -> OK
A5: Total | B5: =SUM(B2:B4) -> 270.84541 | C5: =SUM(C2:C4) -> 0.3241007 | D5: =SUM(D2:D4) -> 36.990924 | E5: =SUM(E2:E4) -> 335253 | F5: =SUM(F2:F4) -> 205000 | G5: =SUM(G2:G4) -> 335253 | H5: =SUM(H2:H4) -> 5111.6872 | I5: =IF(AND(G5>=F5,G5<=E5),"OK","OUT OF RANGE") -> OK

Sheet Solver Model
A1: Solver Model
A2: contact | B2: estimated cac | C2: conversion rate | D2: customers per 1000 | E2: max budget | F2: min budget | G2: budget allocation | H2: expected customers
A3: cellular | B3: ='Channel Summary'!I2 -> 54.094758 | C3: ='Channel Summary'!H2 -> 0.149189 | D3: ='Channel Summary'!J2 -> 18.486079 | E3: ='Solver Table'!E2 -> 220000 | F3: ='Solver Table'!F2 -> 150000 | G3: 220000 | H3: =G3/B3 -> 4066.9375
A4: unknown | B4: ='Channel Summary'!I3 -> 102.71604 | C4: ='Channel Summary'!H3 -> 0.04070661 | D4: ='Channel Summary'!J3 -> 9.735578 | E4: ='Solver Table'!E3 -> 35253 | F4: ='Solver Table'!F3 -> 15000 | G4: 35253 | H4: =G4/B4 -> 343.20833
A5: telephone | B5: ='Channel Summary'!I4 -> 114.03462 | C5: ='Channel Summary'!H4 -> 0.13420509 | D5: ='Channel Summary'!J4 -> 8.7692671 | E5: ='Solver Table'!E4 -> 80000 | F5: ='Solver Table'!F4 -> 40000 | G5: ='Solver Table'!G4 -> 80000 | H5: =G5/B5 -> 701.54137
A7: Total Budget Used | G7: =SUM(G3:G5) -> 335253
A8: Total Expected Customers | H8: =SUM(H3:H5) -> 5111.6872
A9: Overall CAC | H9: =G7/H8 -> 65.585586
A11: Setup
A12: • Max customers model: Set Objective = H8 and choose Max
A13: • Min CAC model: Set Objective = H9 and choose Min, then add H8 >= Inputs!$B$5
A14: • Changing cells = G3:G5
A15: • Common constraints: G7 <= Inputs!$B$4, G3:G5 >= F3:F5, G3:G5 <= E3:E5
A16: •Solving method: Simplex LP
A17: Data: https://archive-beta.ics.uci.edu/dataset/222/bank%2Bmarketing

Sheet Summary
A1: CAC Optimization Summary
A3: Total Budget | B3: =Inputs!B4 -> 335253
A4: Total Expected Customers | B4: ='Solver Model'!H8 -> 5111.6872
A5: Overall CAC | B5: ='Solver Model'!H9 -> 65.585586
A7: Recommended Budget by Channel
A8: Channel | B8: Budget Allocation | C8: Expected Customers | D8: Estimated CAC
A9: ='Solver Model'!A3 -> cellular | B9: ='Solver Model'!G3 -> 220000 | C9: ='Solver Model'!H3 -> 4066.9375 | D9: ='Solver Model'!B3 -> 54.094758
A10: ='Solver Model'!A4 -> unknown | B10: ='Solver Model'!G4 -> 35253 | C10: ='Solver Model'!H4 -> 343.20833 | D10: ='Solver Model'!B4 -> 102.71604
A11: ='Solver Model'!A5 -> telephone | B11: ='Solver Model'!G5 -> 80000 | C11: ='Solver Model'!H5 -> 701.54137 | D11: ='Solver Model'!B5 -> 114.03462
A12: Total | B12: =SUM(B9:B11) -> 335253 | C12: =SUM(C9:C11) -> 5111.6872 | D12: =B12/C12 -> 65.585586
A13: Interpretation
A17: Business Questions
A18: How should the bank allocate its budget to acquire more customers?
A19: Put as much as possible into cellular, set the other two to their minimums, and don't spend a dollar more on telephone than you have to.
A20: Cellular acquires customers at half the cost of telephone. Every dollar shifted from telephone to cellular buys you roughly 2x more customers.

Sheet Sensitivity Analysis
A2: Sensitivity Analysis
A4: Total Budget Sensitivity
B5: Min Budget ($) | C5: Max Budget ($) | D5: CAC ($)
A6: Cellular | B6: ='[1]Solver Table'!F2 -> 150000 | C6: ='[1]Solver Table'!E2 -> 220000 | D6: ='[1]Channel Summary'!I2 -> 54.094758
A7: Unknown | B7: ='[1]Solver Table'!F3 -> 15000 | C7: ='[1]Solver Table'!E3 -> 35253 | D7: ='[1]Channel Summary'!I3 -> 102.71604
A8: Telephone | B8: ='[1]Solver Table'!F4 -> 40000 | C8: ='[1]Solver Table'!E4 -> 80000 | D8: ='[1]Channel Summary'!I4 -> 114.03462
A10: Budget Allocation
A11: Total Budget ($) | B11: Cellular ($) | C11: Unknown ($) | D11: Telephone ($) | E11: Total Customers | F11: Overall CAC ($) | G11: CAC vs Base
A12: 150000 | B12: =MIN($C$6,MAX($B$6,A12-($B$7+$B$8))) -> 150000 | C12: =MIN($C$7,MAX($B$7,A12-B12-$B$8)) -> 15000 | D12: =MIN($C$8,MAX($B$8,A12-B12-C12)) -> 40000 | E12: =B12/$D$6+C12/$D$7+D12/$D$8 -> 3269.7163 | F12: =A12/E12 -> 45.87554 | G12: =F12-$F$16 -> -19.710046
A13: 200000 | B13: =MIN($C$6,MAX($B$6,A13-($B$7+$B$8))) -> 150000 | C13: =MIN($C$7,MAX($B$7,A13-B13-$B$8)) -> 15000 | D13: =MIN($C$8,MAX($B$8,A13-B13-C13)) -> 40000 | E13: =B13/$D$6+C13/$D$7+D13/$D$8 -> 3269.7163 | F13: =A13/E13 -> 61.167387 | G13: =F13-$F$16 -> -4.4181994
A14: 250000 | B14: =MIN($C$6,MAX($B$6,A14-($B$7+$B$8))) -> 195000 | C14: =MIN($C$7,MAX($B$7,A14-B14-$B$8)) -> 15000 | D14: =MIN($C$8,MAX($B$8,A14-B14-C14)) -> 40000 | E14: =B14/$D$6+C14/$D$7+D14/$D$8 -> 4101.5898 | F14: =A14/E14 -> 60.951975 | G14: =F14-$F$16 -> -4.6336116
A15: 300000 | B15: =MIN($C$6,MAX($B$6,A15-($B$7+$B$8))) -> 220000 | C15: =MIN($C$7,MAX($B$7,A15-B15-$B$8)) -> 35253 | D15: =MIN($C$8,MAX($B$8,A15-B15-C15)) -> 44747 | E15: =B15/$D$6+C15/$D$7+D15/$D$8 -> 4802.5442 | F15: =A15/E15 -> 62.46689 | G15: =F15-$F$16 -> -3.1186963
A16: 335253 | B16: =MIN($C$6,MAX($B$6,A16-($B$7+$B$8))) -> 220000 | C16: =MIN($C$7,MAX($B$7,A16-B16-$B$8)) -> 35253 | D16: =MIN($C$8,MAX($B$8,A16-B16-C16)) -> 80000 | E16: =B16/$D$6+C16/$D$7+D16/$D$8 -> 5111.6872 | F16: =A16/E16 -> 65.585586 | G16: 0
A17: 400000 | B17: =MIN($C$6,MAX($B$6,A17-($B$7+$B$8))) -> 220000 | C17: =MIN($C$7,MAX($B$7,A17-B17-$B$8)) -> 35253 | D17: =MIN($C$8,MAX($B$8,A17-B17-C17)) -> 80000 | E17: =B17/$D$6+C17/$D$7+D17/$D$8 -> 5111.6872 | F17: =A17/E17 -> 78.25205 | G17: =F17-$F$16 -> 12.666464
A18: 450000 | B18: =MIN($C$6,MAX($B$6,A18-($B$7+$B$8))) -> 220000 | C18: =MIN($C$7,MAX($B$7,A18-B18-$B$8)) -> 35253 | D18: =MIN($C$8,MAX($B$8,A18-B18-C18)) -> 80000 | E18: =B18/$D$6+C18/$D$7+D18/$D$8 -> 5111.6872 | F18: =A18/E18 -> 88.033556 | G18: =F18-$F$16 -> 22.44797
A19: 500000 | B19: =MIN($C$6,MAX($B$6,A19-($B$7+$B$8))) -> 220000 | C19: =MIN($C$7,MAX($B$7,A19-B19-$B$8)) -> 35253 | D19: =MIN($C$8,MAX($B$8,A19-B19-C19)) -> 80000 | E19: =B19/$D$6+C19/$D$7+D19/$D$8 -> 5111.6872 | F19: =A19/E19 -> 97.815063 | G19: =F19-$F$16 -> 32.229476
A24: CAC Sensitivity to Cost Per Contact
A25: Channel | B25: Base Cost | C25: -0.6 | D25: -0.4 | E25: -0.2 | F25: 0 | G25: 0.2 | H25: 0.4 | I25: 0.6
A26: cellular | B26: 3 | C26: ='Channel Summary'!I2*(1-60%) -> 21.637903 | D26: ='Channel Summary'!I2*(1-40%) -> 32.456855 | E26: ='Channel Summary'!I2*(1-20%) -> 43.275807 | F26: ='Channel Summary'!I2*(1-0%) -> 54.094758 | G26: ='Channel Summary'!I2*(1+20%) -> 64.91371 | H26: ='Channel Summary'!I2*(1+40%) -> 75.732662 | I26: ='Channel Summary'!I2*(1+60%) -> 86.551614
A27: telephone | B27: 4.5 | C27: ='Channel Summary'!I3*(1-60%) -> 41.086415 | D27: ='Channel Summary'!I3*(1-40%) -> 61.629623 | E27: ='Channel Summary'!I3*(1-20%) -> 82.17283 | F27: ='Channel Summary'!I3*(1-0%) -> 102.71604 | G27: ='Channel Summary'!I3*(1+20%) -> 123.25925 | H27: ='Channel Summary'!I3*(1+40%) -> 143.80245 | I27: ='Channel Summary'!I3*(1+60%) -> 164.34566
A28: unknown | B28: 1.5 | C28: ='Channel Summary'!I4*(1-60%) -> 45.613846 | D28: ='Channel Summary'!I4*(1-40%) -> 68.420769 | E28: ='Channel Summary'!I4*(1-20%) -> 91.227692 | F28: ='Channel Summary'!I4*(1-0%) -> 114.03462 | G28: ='Channel Summary'!I4*(1+20%) -> 136.84154 | H28: ='Channel Summary'!I4*(1+40%) -> 159.64846 | I28: ='Channel Summary'!I4*(1+60%) -> 182.45538
A32: Business Questions
A33: What happens if cellular contact costs increase?
A35: Cellular costs would need to nearly double (+90%) before it stops being your cheapest channel. That's an enormous buffer, it remains the best option through almost any realistic cost increase scenario.

Sheet LTV Analysis
A1: LTV Analysis Customer Acquisition Cost Model
A4: ASSUMPTIONS
A5: Input | B5: Value
A6: Avg Annual Revenue per Customer ($) | B6: 200
A7: Avg Retention Period (years) | B7: 2
A8: Annual Churn Rate | B8: 0.5
A9: Discount Rate | B9: 0.1
A10: Gross Margin | B10: 0.6
A12: LTV CALCULATIONS
A13: Method | B13: LTV ($)
A14: Simple LTV | B14: =B6*B7 -> 400
A15: Churn-based LTV | B15: =B6/B8 -> 400
A16: Margin-adjusted LTV | B16: =(B6*B10)/B8 -> 240
A17: Discounted LTV | B17: =(B6*B10)/(B8+B9) -> 200
A19: LTV:CAC RATIO BY CHANNEL
A20: Channel | B20: CAC ($) | C20: LTV ($) (Discounted) | D20: LTV:CAC Ratio | E20: Payback Period (months) | F20: Assessment
A21: Cellular | B21: ='Solver Table'!B2 -> 54.094759 | C21: =$B$17 -> 200 | D21: =C21/B21 -> 3.6972159 | E21: =B21/(B6*B10/12) -> 5.4094759 | F21: =IF(C21/B21>=5,"Excellent",IF(C21/B21>=3,"Healthy",IF(C21/B21>=1,"Marginal","Unprofitable"))) -> Healthy
A22: Unknown | B22: ='Solver Table'!B3 -> 102.71604 | C22: =$B$17 -> 200 | D22: =C22/B22 -> 1.9471156 | E22: =B22/(B6*B10/12) -> 10.271604 | F22: =IF(C22/B22>=5,"Excellent",IF(C22/B22>=3,"Healthy",IF(C22/B22>=1,"Marginal","Unprofitable"))) -> Marginal
A23: Telephone | B23: ='Solver Table'!B4 -> 114.03462 | C23: =$B$17 -> 200 | D23: =C23/B23 -> 1.7538534 | E23: =B23/(B6*B10/12) -> 11.403462 | F23: =IF(C23/B23>=5,"Excellent",IF(C23/B23>=3,"Healthy",IF(C23/B23>=1,"Marginal","Unprofitable"))) -> Marginal
A25: LTV:CAC BENCHMARK GUIDE
A26: Ratio | B26: Assessment | C26: What it means
A27: Below 1x | B27: Unprofitable | C27: Losing money on every customer acquired
A28: 1x – 3x | B28: Marginal | C28: Breakeven, CAC is eating most of the value
A29: 3x – 5x | B29: Healthy | C29: Industry standard target for most businesses
A30: Above 5x | B30: Excellent | C30: Strong unit economics, could justify higher CAC
